README.rst
setup.py
cpinsim/__init__.py
cpinsim/abstract_simulation.py
cpinsim/annotate_constraints.py
cpinsim/constraint_io.py
cpinsim/infinite_simulation.py
cpinsim/protein.py
cpinsim/protein_type.py
cpinsim/proteinparser.py
cpinsim/version.py
cpinsim.egg-info/PKG-INFO
cpinsim.egg-info/SOURCES.txt
cpinsim.egg-info/dependency_links.txt
cpinsim.egg-info/entry_points.txt
cpinsim.egg-info/requires.txt
cpinsim.egg-info/top_level.txt