Metadata-Version: 1.1
Name: cpinsim
Version: 0.5.2
Summary: CPINSim - Constrained Protein Interaction Networks Simulator
Home-page: https://github.com/BiancaStoecker/cpinsim
Author: Bianca Stöcker
Author-email: bianca.stoecker@tu-dortmund.de
License: MIT
Platform: UNKNOWN
Classifier: Development Status :: 4 - Beta
Classifier: Environment :: Console
Classifier: Intended Audience :: Science/Research
Classifier: License :: OSI Approved :: MIT License
Classifier: Natural Language :: English
Classifier: Programming Language :: Python :: 3
Classifier: Topic :: Scientific/Engineering :: Bio-Informatics
